s3insync/__init__.py
s3insync/__main__.py
s3insync/cli.py
s3insync/operations.py
s3insync/repositories.py
s3insync/sync_decider.py
s3insync/cmd/__init__.py
s3insync/cmd/pull.py
s3insync-0.2.1.dist-info/entry_points.txt
s3insync-0.2.1.dist-info/LICENSE
s3insync-0.2.1.dist-info/WHEEL
s3insync-0.2.1.dist-info/METADATA
s3insync-0.2.1.dist-info/RECORD
